dehallucinate_sdk/__init__.py
dehallucinate_sdk/classifier.py
dehallucinate_sdk/client.py
dehallucinate_sdk/config.py
dehallucinate_sdk/semantic_entropy.py
dehallucinate_sdk/sgl_inference.py
dehallucinate_sdk/telemetry.py
dehallucinate_sdk/utils.py
dehallucinate_sdk/SE/__init__.py
dehallucinate_sdk/SE/environment.yaml
dehallucinate_sdk/SE/environment_export.yaml
dehallucinate_sdk/SE/requirements.txt
dehallucinate_sdk/SE/CoNLI/__init__.py
dehallucinate_sdk/SE/CoNLI/run_hallucination_evaluator.py
dehallucinate_sdk/SE/CoNLI/run_hallucination_mitigation.py
dehallucinate_sdk/SE/CoNLI/run_hallucination_sentence_gt_evaluator.py
dehallucinate_sdk/SE/CoNLI/run_response_quality_evaluator.py
dehallucinate_sdk/SE/CoNLI/configs/__init__.py
dehallucinate_sdk/SE/CoNLI/configs/nli_config.py
dehallucinate_sdk/SE/CoNLI/configs/openai_config.py
dehallucinate_sdk/SE/CoNLI/configs/ta_config.py
dehallucinate_sdk/SE/CoNLI/modules/__init__.py
dehallucinate_sdk/SE/CoNLI/modules/entity_detector.py
dehallucinate_sdk/SE/CoNLI/modules/hallucination_detection_prompt.py
dehallucinate_sdk/SE/CoNLI/modules/hallucination_detector.py
dehallucinate_sdk/SE/CoNLI/modules/hallucination_mitigation_prompt.py
dehallucinate_sdk/SE/CoNLI/modules/hallucination_mitigator.py
dehallucinate_sdk/SE/CoNLI/modules/hd_constants.py
dehallucinate_sdk/SE/CoNLI/modules/sentence_selector.py
dehallucinate_sdk/SE/CoNLI/modules/data/__init__.py
dehallucinate_sdk/SE/CoNLI/modules/data/data_loader.py
dehallucinate_sdk/SE/CoNLI/modules/data/response_preprocess.py
dehallucinate_sdk/SE/CoNLI/modules/utils/__init__.py
dehallucinate_sdk/SE/CoNLI/modules/utils/aoai_utils.py
dehallucinate_sdk/SE/CoNLI/modules/utils/conversion_utils.py
dehallucinate_sdk/SE/CoNLI/modules/utils/gpt_output_utils.py
dehallucinate_sdk/SE/CoNLI/modules/utils/sentence_splitter.py
dehallucinate_sdk/SE/CoNLI/prompts/chat_completions/hallucination_detection/generic.nli.v1.yaml
dehallucinate_sdk/SE/CoNLI/prompts/chat_completions/hallucination_mitigation/v3.yaml
hapi_sdk-0.2.23.dist-info/licenses/LICENSE
hapi_sdk-0.2.23.dist-info/METADATA
hapi_sdk-0.2.23.dist-info/WHEEL
hapi_sdk-0.2.23.dist-info/top_level.txt
hapi_sdk-0.2.23.dist-info/RECORD
