Metadata-Version: 2.4
Name: HAPI-SDK
Version: 0.2.23
Summary: A plug-and-play SDK for de-hallucinating outputs from LLMs using semantic entropy and trained classifiers
Home-page: https://github.com/cyprienn967/HAPI_SDK
Author: True
Author-email: True <cyprienseydoux@gmail.com>
Maintainer-email: True <cyprienseydoux@gmail.com>
Project-URL: Homepage, https://github.com/cyprienn967/HAPI_SDK
Project-URL: Bug Reports, https://github.com/cyprienn967/HAPI_SDK/issues
Project-URL: Source, https://github.com/cyprienn967/HAPI_SDK
Keywords: llm,hallucination,detection,ai,nlp,semantic-entropy,machine-learning
Classifier: Development Status :: 4 - Beta
Classifier: Intended Audience :: Developers
Classifier: Intended Audience :: Science/Research
Classifier: Operating System :: OS Independent
Classifier: Programming Language :: Python :: 3
Classifier: Programming Language :: Python :: 3.7
Classifier: Programming Language :: Python :: 3.8
Classifier: Programming Language :: Python :: 3.9
Classifier: Programming Language :: Python :: 3.10
Classifier: Programming Language :: Python :: 3.11
Classifier: Topic :: Scientific/Engineering :: Artificial Intelligence
Classifier: Topic :: Software Development :: Libraries :: Python Modules
Requires-Python: >=3.7
License-File: LICENSE
Requires-Dist: torch
Requires-Dist: transformers
Requires-Dist: numpy
Requires-Dist: pandas
Requires-Dist: scikit-learn
Requires-Dist: tqdm
Requires-Dist: accelerate
Requires-Dist: azure-ai-textanalytics
Requires-Dist: azure-core
Requires-Dist: openai
Requires-Dist: nltk
Requires-Dist: sentence-transformers
Requires-Dist: matplotlib
Requires-Dist: seaborn
Requires-Dist: datasets
Requires-Dist: peft
Requires-Dist: bitsandbytes
Requires-Dist: pytest
Requires-Dist: scipy
Requires-Dist: requests
Requires-Dist: PyYAML
Requires-Dist: Pillow
Requires-Dist: packaging
Requires-Dist: colorama
Requires-Dist: termcolor
Dynamic: author
Dynamic: home-page
Dynamic: license-file
Dynamic: requires-python
